{
  "as_of": "2026-06-17",
  "data_through": "2026-05-31",
  "generated_at": "2026-07-06 14:07",
  "forecast_horizon": "T+12 months",
  "baseline_label": "Base case: tariff-drag slowdown with gradual disinflation. Fed holds H1, cuts 50bp H2. No recession.",
  "optimistic_label": "Upside: inflation normalises faster, growth holds above trend, Fed cuts 75bp. Soft landing.",
  "pessimistic_label": "Downside: tariff-stagflation \u2014 growth disappoints, inflation stays sticky, conditions tighten.",
  "indicators": {
    "g_nfp": {
      "label": "Nonfarm Payrolls (3m avg)",
      "pillar": "growth",
      "latest_actual_date": "2026-05-31",
      "latest_actual_z": 0.1457,
      "latest_actual_raw": "188.3333",
      "next_release": "2026-07-03",
      "forecast_raw": "+148K avg \u2192 +130K by Apr 2027",
      "source": "Bloomberg consensus / BLS",
      "status": "consensus_forecast",
      "in_baseline": true,
      "notes": "Tariff uncertainty slowing hiring pace; 3m avg declining but no recessionary signal",
      "baseline_z": [
        0.1457,
        0.1057,
        0.0757,
        0.0357,
        -0.0043,
        -0.0343,
        -0.0643,
        -0.0843,
        -0.0843,
        -0.0743,
        -0.0543,
        -0.0343
      ],
      "optimistic_z": [
        0.5057,
        0.5357,
        0.5357,
        0.5157,
        0.4857,
        0.4457,
        0.3557,
        0.2957,
        0.2457,
        0.2057,
        0.1957,
        0.1757
      ],
      "pessimistic_z": [
        -0.4643,
        -0.6243,
        -0.6843,
        -0.7243,
        -0.7443,
        -0.7443,
        -0.7243,
        -0.6843,
        -0.6443,
        -0.5943,
        -0.5443,
        -0.4943
      ]
    },
    "g_ipman": {
      "label": "Industrial Production Mfg (YoY)",
      "pillar": "growth",
      "latest_actual_date": "2026-05-31",
      "latest_actual_z": 0.2349,
      "latest_actual_raw": "1.4264",
      "next_release": "2026-07-16",
      "forecast_raw": "Flat \u2192 -1.5% YoY by Q4 2026",
      "source": "Fed industrial release / simulated",
      "status": "simulated",
      "in_baseline": true,
      "notes": "Manufacturing IP faces tariff headwind on imported inputs; estimated from trend and PMI data",
      "baseline_z": [
        0.1609,
        0.1109,
        0.0509,
        0.0109,
        -0.0291,
        -0.0691,
        -0.0991,
        -0.1091,
        -0.0991,
        -0.0791,
        -0.0591,
        -0.0291
      ],
      "optimistic_z": [
        0.4609,
        0.4709,
        0.4509,
        0.4209,
        0.3709,
        0.3109,
        0.2309,
        0.1809,
        0.1509,
        0.1209,
        0.1009,
        0.0809
      ],
      "pessimistic_z": [
        -0.3891,
        -0.5591,
        -0.6391,
        -0.6691,
        -0.6891,
        -0.6891,
        -0.6591,
        -0.6091,
        -0.5691,
        -0.5291,
        -0.4891,
        -0.4491
      ]
    },
    "g_gdp": {
      "label": "Real GDP (YoY)",
      "pillar": "growth",
      "latest_actual_date": "2026-05-31",
      "latest_actual_z": -0.5177,
      "latest_actual_raw": "0.0",
      "next_release": "2026-07-27",
      "forecast_raw": "1.4\u20131.6% \u2192 gradual recovery to ~2.0% by Q1 2027",
      "source": "FOMC SEP / CBO / simulated",
      "status": "consensus_forecast",
      "in_baseline": true,
      "notes": "Quarterly, forward-filled monthly. Q2 2026 soft from tariff drag; partial recovery in H2 as policy uncertainty fades",
      "baseline_z": [
        -0.5207,
        -0.5407,
        -0.5507,
        -0.5307,
        -0.5007,
        -0.4607,
        -0.4107,
        -0.3707,
        -0.3207,
        -0.2807,
        -0.2407,
        -0.2007
      ],
      "optimistic_z": [
        -0.1507,
        -0.1007,
        -0.0507,
        0.0193,
        0.0793,
        0.1293,
        0.1693,
        0.1893,
        0.1993,
        0.1993,
        0.1893,
        0.1793
      ],
      "pessimistic_z": [
        -0.9807,
        -1.1007,
        -1.1407,
        -1.1507,
        -1.1407,
        -1.1007,
        -1.0407,
        -0.9707,
        -0.9107,
        -0.8507,
        -0.7907,
        -0.7307
      ]
    },
    "g_serv": {
      "label": "Real Services Spending (YoY)",
      "pillar": "growth",
      "latest_actual_date": "2026-05-31",
      "latest_actual_z": -0.0038,
      "latest_actual_raw": "2.0461",
      "next_release": "2026-07-27",
      "forecast_raw": "2.0\u20132.3% real YoY \u2192 gradual decel to ~1.7% by Q2 2027",
      "source": "BEA PCE release / simulated",
      "status": "simulated",
      "in_baseline": true,
      "notes": "Services consumption resilient but decelerating; tariff pass-through risk on goods-adjacent services",
      "baseline_z": [
        -0.0838,
        -0.1138,
        -0.1438,
        -0.1738,
        -0.2038,
        -0.2238,
        -0.2438,
        -0.2438,
        -0.2338,
        -0.2238,
        -0.2138,
        -0.1938
      ],
      "optimistic_z": [
        0.3162,
        0.3362,
        0.3362,
        0.3062,
        0.2662,
        0.2162,
        0.1262,
        0.0662,
        0.0162,
        -0.0238,
        -0.0438,
        -0.0638
      ],
      "pessimistic_z": [
        -0.7438,
        -0.9038,
        -0.9638,
        -0.9838,
        -0.9938,
        -0.9938,
        -0.9638,
        -0.9238,
        -0.8738,
        -0.8138,
        -0.7638,
        -0.7138
      ]
    },
    "i_pce_dev": {
      "label": "Core PCE Deviation from 2% Target",
      "pillar": "inflation",
      "latest_actual_date": "2026-05-31",
      "latest_actual_z": -0.9403,
      "latest_actual_raw": "1.412",
      "next_release": "2026-07-27",
      "forecast_raw": "~2.6% \u2192 ~2.1% core PCE by Q1 2027 (gradual disinflation)",
      "source": "Bloomberg consensus / Fed SEP / BEA",
      "status": "consensus_forecast",
      "in_baseline": true,
      "notes": "Inflation pillar primary drag; baseline assumes tariff pass-through is one-time, not persistent",
      "baseline_z": [
        -0.8953,
        -0.8553,
        -0.8053,
        -0.7553,
        -0.7053,
        -0.6553,
        -0.6153,
        -0.5753,
        -0.5453,
        -0.5153,
        -0.4953,
        -0.4753
      ],
      "optimistic_z": [
        -0.0753,
        0.0747,
        0.2147,
        0.3347,
        0.4447,
        0.5247,
        0.5447,
        0.5247,
        0.4847,
        0.4347,
        0.3747,
        0.3147
      ],
      "pessimistic_z": [
        -1.5353,
        -1.5853,
        -1.5953,
        -1.5853,
        -1.5553,
        -1.5053,
        -1.4453,
        -1.3753,
        -1.3053,
        -1.2453,
        -1.1753,
        -1.1153
      ]
    },
    "i_pce_mom": {
      "label": "Core PCE Momentum (6m change in YoY)",
      "pillar": "inflation",
      "latest_actual_date": "2026-05-31",
      "latest_actual_z": -1.0458,
      "latest_actual_raw": "0.5829",
      "next_release": "2026-07-27",
      "forecast_raw": "Decelerating: momentum turns positive as base effects help H2 2026",
      "source": "Bloomberg consensus / BEA",
      "status": "consensus_forecast",
      "in_baseline": true,
      "notes": "6M change in core PCE YoY; improving as 2025 tariff spike rolls off the base",
      "baseline_z": [
        -0.9458,
        -0.8058,
        -0.6558,
        -0.5058,
        -0.3558,
        -0.2158,
        -0.1058,
        -0.0158,
        0.0442,
        0.0842,
        0.0842,
        0.0642
      ],
      "optimistic_z": [
        -0.3258,
        -0.1058,
        0.1642,
        0.4042,
        0.6142,
        0.7842,
        0.8542,
        0.8642,
        0.8142,
        0.7342,
        0.6442,
        0.5342
      ],
      "pessimistic_z": [
        -1.5658,
        -1.5258,
        -1.4558,
        -1.3758,
        -1.2758,
        -1.1758,
        -1.0758,
        -0.9758,
        -0.8858,
        -0.8058,
        -0.7258,
        -0.6558
      ]
    },
    "l_nfci": {
      "label": "Financial Conditions Index (NFCI)",
      "pillar": "liquidity",
      "latest_actual_date": "2026-05-31",
      "latest_actual_z": 0.2944,
      "latest_actual_raw": "-0.5042",
      "next_release": "2026-06-26",
      "forecast_raw": "Slight easing: NFCI normalises as rate cut expectations build",
      "source": "Chicago Fed / market-implied",
      "status": "market_implied",
      "in_baseline": true,
      "notes": "Fed funds futures imply 2 cuts in H2 2026; NFCI should ease gradually",
      "baseline_z": [
        0.2994,
        0.2794,
        0.2594,
        0.2394,
        0.2194,
        0.2094,
        0.2194,
        0.2394,
        0.2494,
        0.2494,
        0.2394,
        0.2394
      ],
      "optimistic_z": [
        0.5994,
        0.5894,
        0.5694,
        0.5294,
        0.4994,
        0.4894,
        0.4894,
        0.4894,
        0.4794,
        0.4594,
        0.4394,
        0.4194
      ],
      "pessimistic_z": [
        -0.0006,
        -0.1206,
        -0.2006,
        -0.2506,
        -0.2906,
        -0.3106,
        -0.2906,
        -0.2606,
        -0.2306,
        -0.2006,
        -0.1806,
        -0.1606
      ]
    },
    "l_curve": {
      "label": "Yield Curve (10Y-2Y)",
      "pillar": "liquidity",
      "latest_actual_date": "2026-05-31",
      "latest_actual_z": -0.6006,
      "latest_actual_raw": "0.47",
      "next_release": "2026-06-30",
      "forecast_raw": "Normalising: 10Y-2Y \u2192 +0bps to +30bps range as Fed cuts front end",
      "source": "Fed funds futures / market-implied",
      "status": "market_implied",
      "in_baseline": true,
      "notes": "Curve inversion (-60bp currently) expected to normalise with Fed cuts; not recessionary inversion at current level",
      "baseline_z": [
        -0.5996,
        -0.5596,
        -0.5096,
        -0.4596,
        -0.3996,
        -0.3396,
        -0.2696,
        -0.2096,
        -0.1496,
        -0.0996,
        -0.0596,
        -0.0296
      ],
      "optimistic_z": [
        -0.1796,
        -0.0996,
        -0.0196,
        0.0604,
        0.1404,
        0.2104,
        0.2704,
        0.3104,
        0.3304,
        0.3404,
        0.3304,
        0.3204
      ],
      "pessimistic_z": [
        -0.9196,
        -0.9696,
        -0.9996,
        -1.0096,
        -0.9996,
        -0.9696,
        -0.9196,
        -0.8696,
        -0.8196,
        -0.7596,
        -0.7096,
        -0.6596
      ]
    },
    "c_ig_level": {
      "label": "Credit Spread Level (BAA-10Y)",
      "pillar": "credit",
      "latest_actual_date": "2026-05-31",
      "latest_actual_z": 1.1335,
      "latest_actual_raw": "1.62",
      "next_release": "2026-06-30",
      "forecast_raw": "Normalising from historically tight: spreads widen modestly to ~120-130bp from ~100bp",
      "source": "Moody's / FRED / simulated",
      "status": "simulated",
      "in_baseline": true,
      "notes": "Current spreads at 23-year tight; expected to widen modestly as growth slows but no recession-level widening",
      "baseline_z": [
        1.1295,
        1.0595,
        0.9895,
        0.9295,
        0.8795,
        0.8395,
        0.7995,
        0.7695,
        0.7495,
        0.7295,
        0.7095,
        0.6895
      ],
      "optimistic_z": [
        1.4195,
        1.3895,
        1.3595,
        1.3095,
        1.2495,
        1.1895,
        1.0995,
        1.0395,
        0.9895,
        0.9395,
        0.8995,
        0.8595
      ],
      "pessimistic_z": [
        0.5395,
        0.3495,
        0.2095,
        0.0995,
        0.0195,
        -0.0305,
        -0.0605,
        -0.0705,
        -0.0705,
        -0.0705,
        -0.0605,
        -0.0505
      ]
    },
    "c_ig_mom": {
      "label": "Credit Spread Momentum (6m change)",
      "pillar": "credit",
      "latest_actual_date": "2026-05-31",
      "latest_actual_z": 0.2316,
      "latest_actual_raw": "-0.15",
      "next_release": "2026-06-30",
      "forecast_raw": "Deteriorating: spreads widening vs 6m ago as tightening cycle reverses",
      "source": "Moody's / FRED / simulated",
      "status": "simulated",
      "in_baseline": true,
      "notes": "Momentum turns negative as current tight spreads start widening vs the 6m-lagged base",
      "baseline_z": [
        0.2296,
        0.1596,
        0.0896,
        0.0396,
        -0.0004,
        -0.0304,
        -0.0404,
        -0.0404,
        -0.0304,
        -0.0204,
        -0.0104,
        -0.0004
      ],
      "optimistic_z": [
        0.5396,
        0.4996,
        0.4396,
        0.3796,
        0.3196,
        0.2696,
        0.2396,
        0.2096,
        0.1796,
        0.1496,
        0.1296,
        0.1096
      ],
      "pessimistic_z": [
        -0.3804,
        -0.5304,
        -0.6004,
        -0.6304,
        -0.6404,
        -0.6304,
        -0.6004,
        -0.5604,
        -0.5204,
        -0.4804,
        -0.4404,
        -0.4004
      ]
    },
    "s_vix": {
      "label": "VIX (monthly average)",
      "pillar": "stress",
      "latest_actual_date": "2026-05-31",
      "latest_actual_z": 0.3283,
      "latest_actual_raw": "17.2371",
      "next_release": "2026-06-30",
      "forecast_raw": "VIX normalises toward 18-20 range as trade policy uncertainty eases",
      "source": "CBOE / FRED / market-implied",
      "status": "market_implied",
      "in_baseline": true,
      "notes": "Current VIX near long-run avg; baseline assumes gradual drift lower as uncertainty resolves",
      "baseline_z": [
        0.3303,
        0.2903,
        0.2603,
        0.2403,
        0.2203,
        0.2103,
        0.2003,
        0.2003,
        0.1903,
        0.1903,
        0.1803,
        0.1803
      ],
      "optimistic_z": [
        0.6103,
        0.5903,
        0.5603,
        0.5203,
        0.4803,
        0.4403,
        0.3903,
        0.3503,
        0.3103,
        0.2803,
        0.2603,
        0.2403
      ],
      "pessimistic_z": [
        -0.1997,
        -0.3797,
        -0.4497,
        -0.4897,
        -0.5097,
        -0.5197,
        -0.4997,
        -0.4797,
        -0.4497,
        -0.4297,
        -0.3997,
        -0.3797
      ]
    },
    "s_bond": {
      "label": "Bond / Financial Stress Index",
      "pillar": "stress",
      "latest_actual_date": "2026-05-31",
      "latest_actual_z": 0.4435,
      "latest_actual_raw": "-0.3799",
      "next_release": "2026-06-26",
      "forecast_raw": "Stable: bond vol stays low, no acute stress event expected",
      "source": "St. Louis Fed / FRED DGS10 / market-implied",
      "status": "market_implied",
      "in_baseline": true,
      "notes": "DGS10 realized vol currently low; baseline assumes slow drift lower as curve normalises",
      "baseline_z": [
        0.4395,
        0.3995,
        0.3695,
        0.3395,
        0.3095,
        0.2895,
        0.2695,
        0.2595,
        0.2395,
        0.2295,
        0.2195,
        0.2095
      ],
      "optimistic_z": [
        0.6895,
        0.6695,
        0.6395,
        0.5995,
        0.5495,
        0.5095,
        0.4595,
        0.4195,
        0.3795,
        0.3495,
        0.3195,
        0.2995
      ],
      "pessimistic_z": [
        -0.0605,
        -0.2105,
        -0.2905,
        -0.3305,
        -0.3505,
        -0.3605,
        -0.3405,
        -0.3205,
        -0.3005,
        -0.2805,
        -0.2605,
        -0.2405
      ]
    },
    "s_spy_dd": {
      "label": "Equity Drawdown (SPY from peak)",
      "pillar": "stress",
      "latest_actual_date": "2026-05-31",
      "latest_actual_z": 0.8277,
      "latest_actual_raw": "0.0",
      "next_release": "2026-06-30",
      "forecast_raw": "Mild correction risk: SPY drawdown drifts to -3% to -5% range",
      "source": "Yahoo Finance / market-implied",
      "status": "market_implied",
      "in_baseline": true,
      "notes": "Currently near all-time high (0% drawdown); baseline assumes modest correction as growth slows",
      "baseline_z": [
        0.8297,
        0.7797,
        0.7297,
        0.6897,
        0.6497,
        0.6197,
        0.5997,
        0.5797,
        0.5597,
        0.5497,
        0.5397,
        0.5297
      ],
      "optimistic_z": [
        1.1297,
        1.1097,
        1.0697,
        1.0197,
        0.9597,
        0.8897,
        0.8197,
        0.7597,
        0.6997,
        0.6497,
        0.6097,
        0.5697
      ],
      "pessimistic_z": [
        0.2297,
        -0.0003,
        -0.1203,
        -0.1903,
        -0.2403,
        -0.2603,
        -0.2503,
        -0.2403,
        -0.2203,
        -0.2003,
        -0.1803,
        -0.1703
      ]
    }
  }
}